{"version":1,"resource":"file:///home/mistkyu/Projects/work_projects/mistkyues-bot/requirements.txt","entries":[{"id":"MRg7.txt","timestamp":1739791522897},{"id":"4G90.txt","timestamp":1739799717416},{"id":"smgM.txt","timestamp":1739799810254},{"id":"M9l2.txt","timestamp":1739799871942},{"id":"v7ks.txt","timestamp":1739800125288},{"id":"XLoP.txt","timestamp":1742059234903},{"id":"6k5v.txt","timestamp":1742060808903},{"id":"J3Wk.txt","timestamp":1742123272810},{"id":"VLWP.txt","timestamp":1742128819362},{"id":"Xg2y.txt","source":"undoRedo.source","timestamp":1742128830584}]}